dgf_translate/__init__.py
dgf_translate/dgf_to_geojson.py
dgf_translate-0.0.4.dist-info/METADATA
dgf_translate-0.0.4.dist-info/WHEEL
dgf_translate-0.0.4.dist-info/top_level.txt
dgf_translate-0.0.4.dist-info/RECORD
