Metadata-Version: 2.1
Name: dgf-translate
Version: 0.0.4
Summary: A python package to convert dfg file to GIS readable format such as geojson
Home-page: https://github.com/Kumail09/dgf-translate
Author: Kumail Raza
Author-email: kumail0691@gmail.com
Project-URL: Bug Tracker, https://github.com/Kumail09/dgf-translate/issues
Classifier: Programming Language :: Python :: 3
Classifier: Operating System :: OS Independent
Requires-Python: >=3
